{
  "Version": "2012-10-17",
  "Statement": [
    {
      "Sid": "SecretsManagerReadOnly",
      "Effect": "Allow",
      "Action": [
        "secretsmanager:GetSecretValue"
      ],
      "Resource": "arn:aws:secretsmanager:us-east-1:ACCOUNT_ID:secret:APP_NAME/*"
    },
    {
      "Sid": "S3BucketAccess",
      "Effect": "Allow",
      "Action": [
        "s3:GetObject",
        "s3:PutObject",
        "s3:DeleteObject"
      ],
      "Resource": "arn:aws:s3:::BUCKET_NAME/*"
    },
    {
      "Sid": "S3BucketList",
      "Effect": "Allow",
      "Action": "s3:ListBucket",
      "Resource": "arn:aws:s3:::BUCKET_NAME"
    },
    {
      "Sid": "CloudWatchMetrics",
      "Effect": "Allow",
      "Action": [
        "cloudwatch:PutMetricData"
      ],
      "Resource": "*",
      "Condition": {
        "StringEquals": {
          "cloudwatch:namespace": "MyApp/Production"
        }
      }
    },
    {
      "Sid": "XRayTracing",
      "Effect": "Allow",
      "Action": [
        "xray:PutTraceSegments",
        "xray:PutTelemetryRecords"
      ],
      "Resource": "*"
    }
  ]
}
